deepne/__init__.py
deepne-0.0.0.dist-info/METADATA
deepne-0.0.0.dist-info/WHEEL
deepne-0.0.0.dist-info/top_level.txt
deepne-0.0.0.dist-info/RECORD
