Metadata-Version: 2.2
Name: deepne
Version: 0.0.0
Summary: DeepNe
Author-email: David Bonet <davidbonetsole@gmail.com>
Requires-Python: >=3.8
